odoo/addons/operating_unit/README.rst
odoo/addons/operating_unit/__init__.py
odoo/addons/operating_unit/__manifest__.py
odoo/addons/operating_unit/data/operating_unit_data.xml
odoo/addons/operating_unit/demo/operating_unit_demo.xml
odoo/addons/operating_unit/i18n/operating_unit.pot
odoo/addons/operating_unit/models/__init__.py
odoo/addons/operating_unit/models/operating_unit.py
odoo/addons/operating_unit/models/res_users.py
odoo/addons/operating_unit/readme/CONFIGURE.rst
odoo/addons/operating_unit/readme/CONTRIBUTORS.rst
odoo/addons/operating_unit/readme/DESCRIPTION.rst
odoo/addons/operating_unit/readme/ROADMAP.rst
odoo/addons/operating_unit/readme/USAGE.rst
odoo/addons/operating_unit/security/ir.model.access.csv
odoo/addons/operating_unit/security/operating_unit_security.xml
odoo/addons/operating_unit/static/description/icon.png
odoo/addons/operating_unit/static/description/index.html
odoo/addons/operating_unit/tests/__init__.py
odoo/addons/operating_unit/tests/test_operating_unit.py
odoo/addons/operating_unit/view/operating_unit_view.xml
odoo/addons/operating_unit/view/res_users_view.xml
odoo12_addon_operating_unit-12.0.1.4.0.dist-info/METADATA
odoo12_addon_operating_unit-12.0.1.4.0.dist-info/WHEEL
odoo12_addon_operating_unit-12.0.1.4.0.dist-info/top_level.txt
odoo12_addon_operating_unit-12.0.1.4.0.dist-info/RECORD
